pyUSDforex/__init__.py
pyUSDforex-0.1.3.1.dist-info/LICENSE
pyUSDforex-0.1.3.1.dist-info/METADATA
pyUSDforex-0.1.3.1.dist-info/WHEEL
pyUSDforex-0.1.3.1.dist-info/top_level.txt
pyUSDforex-0.1.3.1.dist-info/RECORD
