Metadata-Version: 2.1
Name: pyUSDforex
Version: 0.1.3.1
Summary: Converts foreign fiat currencies to USD by getting and caching hourly exchanges rates from openexchangerates.org
Home-page: https://github.com/getorca/pyUSDforex
Author: Lawrence Stewart
Author-email: lawrence@lawrencestewart.ca
License: UNKNOWN
Platform: UNKNOWN
Classifier: Programming Language :: Python :: 3
Classifier: License :: OSI Approved :: MIT License
Classifier: Operating System :: OS Independent
